dockerscript/__init__.py
dockerscript/image.py
dockerscript/operations/__init__.py
dockerscript/operations/base_image.py
dockerscript/operations/base_operation.py
dockerscript/operations/command.py
dockerscript/operations/copy.py
dockerscript/operations/environment.py
dockerscript/operations/expose.py
dockerscript/operations/healthcheck.py
dockerscript/operations/label.py
dockerscript/operations/run.py
dockerscript/operations/shell.py
dockerscript/operations/workdir.py
dockerscript-0.8.0.dist-info/DESCRIPTION.rst
dockerscript-0.8.0.dist-info/METADATA
dockerscript-0.8.0.dist-info/RECORD
dockerscript-0.8.0.dist-info/WHEEL
dockerscript-0.8.0.dist-info/metadata.json
dockerscript-0.8.0.dist-info/top_level.txt
tests/__init__.py
tests/test_image.py
tests/operations/__init__.py
tests/operations/test_base_image.py
tests/operations/test_command.py
tests/operations/test_copy.py
tests/operations/test_environment.py
tests/operations/test_expose.py
tests/operations/test_healthcheck.py
tests/operations/test_label.py
tests/operations/test_run.py
tests/operations/test_shell.py
tests/operations/test_workdir.py
