Metadata-Version: 2.0
Name: dockerscript
Version: 0.8.0
Summary: Tool for generating Dockerfiles from Python
Home-page: https://github.com/durandj/dockerscript
Author: James Durand
Author-email: james.durand@alumni.msoe.edu
License: MIT license
Keywords: dockerscript
Platform: UNKNOWN
Classifier: Development Status :: 2 - Pre-Alpha
Classifier: Intended Audience :: Developers
Classifier: License :: OSI Approved :: MIT License
Classifier: Natural Language :: English
Classifier: Programming Language :: Python :: 3.6
Requires-Dist: colored (==1.3.4)
